whole/Run.py
whole/TCP_UDP.py
whole/__init__.py
whole/w.py
whole-1.0.0.0.0.7.dist-info/METADATA
whole-1.0.0.0.0.7.dist-info/WHEEL
whole-1.0.0.0.0.7.dist-info/entry_points.txt
whole-1.0.0.0.0.7.dist-info/top_level.txt
whole-1.0.0.0.0.7.dist-info/RECORD
