Metadata-Version: 2.1
Name: whole
Version: 1.0.0.0.0.7
Requires-Dist: mysql-connector
Requires-Dist: xlrd ==1.2.0
